{
    "Strollin' Stu": {
        "Enums": {},
        "Structs": {
            "LightInfo": {
                "ID": {
                    "Type": "INT",
                    "ArraySize": 1
                },
                "Name": {
                    "Type": "STRING",
                    "ArraySize": 1
                }
            }
        },
        "Members": {
            "Transform": {
                "Type": "TRANSFORM",
                "ArraySize": 1
            },
            "Character": {
                "Type": "STRING",
                "ArraySize": 1
            },
            "LightNum": {
                "Type": "INT",
                "ArraySize": 1
            },
            "LightArray": {
                "Type": "LightInfo",
                "ArraySize": "LightNum"
            },
            "Manager": {
                "Type": "STRING",
                "ArraySize": 1
            },
            "Rail": {
                "Type": "STRING",
                "ArraySize": 1
            },
            "SpawnID": {
                "Type": "INT",
                "ArraySize": 1
            }
        },
        "Wizard": {
            "Default": {
                "Name": "ハムクリ",
                "Dependencies": {
                    "Managers": {
                        "HamuKuriManager": {
                            "Name": "ハムクリマネージャー",
                            "Ancestry": [
                                "全体シーン",
                                "コンダクター初期化用"
                            ]
                        },
                        "EffectColumWaterManager": {
                            "Name": "エフェクト水柱マネージャー",
                            "Ancestry": [
                                "全体シーン",
                                "コンダクター初期化用"
                            ]
                        }
                    },
                    "TablesBin": {},
                    "AssetPaths": []
                },
                "Members": {
                    "Transform": [
                        [
                            0,
                            0,
                            0
                        ],
                        [
                            0,
                            0,
                            0
                        ],
                        [
                            1,
                            1,
                            1
                        ]
                    ],
                    "Character": "ハムクリマネージャー キャラ",
                    "LightNum": 0,
                    "LightArray": {
                        "ID": 0,
                        "Name": "なし"
                    },
                    "Manager": "ハムクリマネージャー",
                    "Rail": "(null)",
                    "SpawnID": -1
                }
            }
        },
        "Rendering": {
            "Default": {
                "Animations": [ "hamukurianm/hamukuri_wait.bck" ],
                "Model": "hamukuri/default.bmd",
                "Textures": {
                    "H_ma_rak_dummy": "map/pollution/h_ma_rak.bti"
                }
            }
        }
    }
}